external_markdown/plugin.py
poetry_mkdocs_test-0.0.5.dist-info/entry_points.txt
poetry_mkdocs_test-0.0.5.dist-info/LICENSE.md
poetry_mkdocs_test-0.0.5.dist-info/WHEEL
poetry_mkdocs_test-0.0.5.dist-info/METADATA
poetry_mkdocs_test-0.0.5.dist-info/RECORD
