Metadata-Version: 2.1
Name: poetry-mkdocs-test
Version: 0.0.5
Summary: Mkdocs plugin that allow to inject external markdown or markdown section from given url
Home-page: https://3os.org/guides/markdown-cheatsheet/external-markdown/
License: MIT
Keywords: mkdocs,plugin,markdown,external-markdown,embed,external,markdown-section
Author: fire1ce
Author-email: dev@3os.org
Requires-Python: >=3.6,<4.0
Classifier: License :: OSI Approved :: MIT License
Classifier: Programming Language :: Python :: 3
Classifier: Programming Language :: Python :: 3.10
Classifier: Programming Language :: Python :: 3.6
Classifier: Programming Language :: Python :: 3.7
Classifier: Programming Language :: Python :: 3.8
Classifier: Programming Language :: Python :: 3.9
Requires-Dist: Jinja2 (>=3.0.3,<4.0.0)
Requires-Dist: mkdocs (>=1.2.3,<2.0.0)
Requires-Dist: requests (>=2.27.1,<3.0.0)
Project-URL: Repository, https://github.com/fire1ce/mkdocs-embed-external-markdown
